CHANGES.md
LICENSE
MANIFEST.in
README.md
setup.cfg
setup.py
vgkits/__init__.py
vgkits/esptool.py
vgkits/miniterm.py
vgkits/vanguard/__init__.py
vgkits/vanguard/__main__.py
vgkits/vanguard/brainfreeze/__init__.py
vgkits/vanguard/brainfreeze/__main__.py
vgkits/vanguard/brainwash/__init__.py
vgkits/vanguard/brainwash/__main__.py
vgkits/vanguard/data/firmware/circuitpython-2.3.1.bin
vgkits/vanguard/data/firmware/circuitpython-3.0.0-beta.1.bin
vgkits/vanguard/data/firmware/esp8266basic-3.0alpha.bin
vgkits/vanguard/data/firmware/espruino-1v99.bin
vgkits/vanguard/data/firmware/micropython+blinka-0.0.0.bin
vgkits/vanguard/data/firmware/micropython-1.10.0.bin
vgkits/vanguard/data/firmware/micropython-1.9.3.bin
vgkits/vanguard/data/firmware/micropython-1.9.4.bin
vgkits/vanguard/data/firmware/nodemcu-1.5.4.1.bin
vgkits/vanguard/data/firmware/punyforth-0.5.bin
vgkits/vanguard/data/firmware/vanguard+rainbow-0.1.0.bin
vgkits/vanguard/shell/__init__.py
vgkits/vanguard/shell/__main__.py
vgkits_vanguard.egg-info/PKG-INFO
vgkits_vanguard.egg-info/SOURCES.txt
vgkits_vanguard.egg-info/dependency_links.txt
vgkits_vanguard.egg-info/entry_points.txt
vgkits_vanguard.egg-info/not-zip-safe
vgkits_vanguard.egg-info/requires.txt
vgkits_vanguard.egg-info/top_level.txt