Metadata-Version: 2.1
Name: vgkits-vanguard
Version: 0.2.0rc12
Summary: Tools to support VGkits Vanguard ESP8266 python-programmable board.
Home-page: https://vgkits.org
Author: @cefn
Author-email: github.com@cefn.com
License: GPL3
Download-URL: https://github.com/vgkits/vgkits-vanguard/archive/0.2.0_rc12.tar.gz
Keywords: vgkits,vanguard,esp8266,micropython,circuitpython,iot,gcse,computer science
Platform: UNKNOWN
Classifier: Development Status :: 4 - Beta
Classifier: Intended Audience :: Developers
Classifier: Intended Audience :: Education
Classifier: License :: OSI Approved :: GNU General Public License v3 (GPLv3)
Classifier: Operating System :: POSIX
Classifier: Operating System :: Microsoft :: Windows
Classifier: Topic :: Education
Classifier: Topic :: Software Development :: Embedded Systems
Classifier: Programming Language :: Python :: 2.7
Classifier: Programming Language :: Python :: 3.3
